cerberus_kind/__init__.py
cerberus_kind/utils.py
cerberus_kind/validator.py
cerberus_kind-0.0.17.dist-info/LICENSE
cerberus_kind-0.0.17.dist-info/METADATA
cerberus_kind-0.0.17.dist-info/WHEEL
cerberus_kind-0.0.17.dist-info/top_level.txt
cerberus_kind-0.0.17.dist-info/RECORD
