Metadata-Version: 2.1
Name: cerberus-kind
Version: 0.0.17
Summary: Help to select a schema by "kind" key on cerberus.
Home-page: https://github.com/onetop21/cerberus-kind.git
Author: Hyoil LEE
Author-email: onetop21@gmail.com
License: MIT License
Platform: UNKNOWN
Requires-Python: >=3.0
License-File: LICENSE
Requires-Dist: Cerberus (<2,>=1.3.4)
